setup.py
bin/tagfix
bin/tagtool
tagtool/__init__.py
tagtool/commands.py
tagtool/is_tagged.py
tagtool/version.py
tagtool.egg-info/PKG-INFO
tagtool.egg-info/SOURCES.txt
tagtool.egg-info/dependency_links.txt
tagtool.egg-info/pbr.json
tagtool.egg-info/requires.txt
tagtool.egg-info/top_level.txt