Metadata-Version: 1.1
Name: tagtool
Version: 1.0.5
Summary: Tagtool allows you to perform mass ID3 tag cleaning operations.
Home-page: https://github.com/dufferzafar/tagtool
Author: Shadab Zafar
Author-email: dufferzafar0@gmail.com
License: MIT
Platform: UNKNOWN
Classifier: Environment :: Console
Classifier: License :: OSI Approved :: MIT License
Classifier: Operating System :: MacOS :: MacOS X
Classifier: Operating System :: Unix
Classifier: Operating System :: POSIX
Classifier: Programming Language :: Python
Classifier: Programming Language :: Python :: 2.7
Classifier: Programming Language :: Python :: 3.4
